setup.py
ywAUT/Devices.py
ywAUT/Devices_s.py
ywAUT/Devices_stf.py
ywAUT/Driver.py
ywAUT/Globalvar.py
ywAUT/ReadConfig.py
ywAUT/__init__.py
ywAUT/__main__.py
ywAUT.egg-info/PKG-INFO
ywAUT.egg-info/SOURCES.txt
ywAUT.egg-info/dependency_links.txt
ywAUT.egg-info/requires.txt
ywAUT.egg-info/top_level.txt