Metadata-Version: 1.0
Name: ywAUT
Version: 0.0.3
Summary: yw-stf-behava-u2
Home-page: http://git.code.oa.com/yuewen-test/u2_stf_automator.git
Author: HanjieFeng
Author-email: 26736548@qq.com
License: MIT Licence
Keywords: pip,ywAUT,featureextraction
Platform: any
